{
    "homepage": "https://github.com/scayssials/scoomander",
    "version": "0.45",
    "url": "https://github.com/scayssials/scoomander/archive/v0.45.zip",
    "hash": "6a1242003e95fe122c1c01358f36efdf11d7632125f576fa073fc434a349b5bd",
    "extract_dir": "scoomander-0.45",
    "bin": "bin/scoomander.ps1",
    "checkver": "github",
    "autoupdate": {
        "url": "https://github.com/scayssials/scoomander/archive/v$version.zip",
        "extract_dir": "scoomander-$version"
    },
    "persist": [
        "config",
        "plugins"
    ]
}
